dingtalk_python_sdk/__init__.py
dingtalk_python_sdk/robot.py
dingtalk_python_sdk-0.0.1.dist-info/METADATA
dingtalk_python_sdk-0.0.1.dist-info/RECORD
dingtalk_python_sdk-0.0.1.dist-info/WHEEL
dingtalk_python_sdk-0.0.1.dist-info/top_level.txt
