Metadata-Version: 2.1
Name: dingtalk-python-sdk
Version: 0.0.1
Summary: A Python library for the DingTalk
Home-page: https://github.com/jiasir/dingtalk-python-sdk
Author: jiasir
Author-email: jiasir@icloud.com
License: MIT
Keywords: dingtalk python sdk
Platform: UNKNOWN
Classifier: Development Status :: 3 - Alpha
Classifier: Intended Audience :: Developers
Classifier: Topic :: Software Development :: Build Tools
Classifier: License :: OSI Approved :: MIT License
Classifier: Programming Language :: Python :: 3
Classifier: Programming Language :: Python :: 3.4
Classifier: Programming Language :: Python :: 3.5
Classifier: Programming Language :: Python :: 3.6
